COPYING
README.rst
setup.py
tests/test_abelian_cover.py
tests/test_angles.py
tests/test_automaton.py
tests/test_flip.py
tests/test_flip_sequence.py
tests/test_flip_sequence_arithmetic.py
tests/test_geometric_polytope.py
tests/test_permutation.py
tests/test_quadrangulation_flip_sequence.py
tests/test_reconstruction.py
tests/test_triangulation_comparison.py
tests/test_triangulation_isomorphism.py
tests/test_triangulation_relabel.py
tests/test_veering.py
veerer/__init__.py
veerer/automaton.py
veerer/constants.py
veerer/cover.py
veerer/features.py
veerer/flat_structure.py
veerer/flip_sequence.py
veerer/layout.py
veerer/linear_family.py
veerer/measured_train_track.py
veerer/misc.py
veerer/permutation.c
veerer/permutation.pyx
veerer/tatami_decomposition.py
veerer/triangulation.py
veerer/veering_quadrangulation.py
veerer/veering_triangulation.py
veerer/version.py
veerer.egg-info/PKG-INFO
veerer.egg-info/SOURCES.txt
veerer.egg-info/dependency_links.txt
veerer.egg-info/top_level.txt
veerer/polyhedron/__init__.py
veerer/polyhedron/cone.py
veerer/polyhedron/linear_algebra.py
veerer/polyhedron/linear_expression.py