Metadata-Version: 2.1
Name: veerer
Version: 0.2.0
Summary: A Python module to manipulate Veering triangulations and their associated flat structures
Home-page: https://github.com/flatsurf/veerer
Author: Mark Bell, Vincent Delecroix, and Saul Schleimer
Author-email: contact@flatsurf.org
License: GPL 2.0+
Classifier: Development Status :: 4 - Beta
Classifier: Intended Audience :: Science/Research
Classifier: License :: OSI Approved :: GNU General Public License v2 or later (GPLv2+)
Classifier: Natural Language :: English
Classifier: Operating System :: OS Independent
Classifier: Programming Language :: Python
Classifier: Topic :: Scientific/Engineering :: Mathematics
License-File: COPYING
